pymatchit/__init__.py
pymatchit/core.py
pymatchit/datasets.py
pymatchit/diagnostics.py
pymatchit/distance.py
pymatchit/matchers.py
pymatchit/plotting.py
pymatchit/data/__init__.py
pymatchit/data/lalonde.csv
pymatchit_causal-0.1.3.dist-info/licenses/LICENSE
pymatchit_causal-0.1.3.dist-info/METADATA
pymatchit_causal-0.1.3.dist-info/WHEEL
pymatchit_causal-0.1.3.dist-info/top_level.txt
pymatchit_causal-0.1.3.dist-info/RECORD
