Metadata-Version: 2.4
Name: pymatchit-causal
Version: 0.1.3
Summary: Propensity Score Matching (PSM), Coarsened Exact Matching (CEM), and Causal Inference in Python. A port of R's MatchIt.
Author-email: Jonas Tünnermann <jonas.tuennermann@freenet.de>
License: MIT License
Project-URL: Homepage, https://github.com/jtuenner/pymatchit
Project-URL: Bug Tracker, https://github.com/jtuenner/pymatchit/issues
Keywords: causal-inference,propensity-score-matching,psm,matching,cem,coarsened-exact-matching,mahalanobis,observational-studies,matchit
Classifier: Programming Language :: Python :: 3
Classifier: License :: OSI Approved :: MIT License
Classifier: Operating System :: OS Independent
Classifier: Topic :: Scientific/Engineering :: Mathematics
Classifier: Topic :: Scientific/Engineering :: Information Analysis
Requires-Python: >=3.9
License-File: LICENSE
Requires-Dist: numpy>=1.21
Requires-Dist: pandas>=1.3
Requires-Dist: scipy~=1.7
Requires-Dist: statsmodels~=0.13
Requires-Dist: matplotlib~=3.5
Requires-Dist: scikit-learn~=1.0
Requires-Dist: seaborn~=0.11
Requires-Dist: patsy~=0.5
Provides-Extra: dev
Requires-Dist: pytest; extra == "dev"
Requires-Dist: ruff; extra == "dev"
Requires-Dist: jupyter; extra == "dev"
Dynamic: license-file
